nonebot_plugin_oachat/__init__.py
nonebot_plugin_oachat/utils.py
nonebot_plugin_oachat-0.1.8.dist-info/LICENSE
nonebot_plugin_oachat-0.1.8.dist-info/METADATA
nonebot_plugin_oachat-0.1.8.dist-info/WHEEL
nonebot_plugin_oachat-0.1.8.dist-info/RECORD
