Metadata-Version: 2.1
Name: nonebot-plugin-oachat
Version: 0.1.8
Summary: A nonebot2 plugin package for openai api chatBot
Home-page:  
License: MIT
Author: Gin2O
Author-email: wulun0102@outlook.com
Requires-Python: >=3.10,<4.0
Classifier: License :: OSI Approved :: MIT License
Classifier: Programming Language :: Python :: 3
Classifier: Programming Language :: Python :: 3.10
Classifier: Programming Language :: Python :: 3.11
Requires-Dist: aiohttp (>=3.8.4,<4.0.0)
Requires-Dist: httpx (>=0.23.3,<0.24.0)
Requires-Dist: nonebot-adapter-onebot (>=2.2.1,<3.0.0)
Requires-Dist: nonebot2 (>=2.0.0rc3,<3.0.0)
Requires-Dist: openai (>=0.26.5,<0.27.0)
Project-URL: Repository, https://github.com/gin2o/nonebot_plugin_oachat
